SpacemanX/SpacemanX.py
SpacemanX/__init__.py
SpacemanX-0.99.dist-info/LICENSE
SpacemanX-0.99.dist-info/METADATA
SpacemanX-0.99.dist-info/WHEEL
SpacemanX-0.99.dist-info/top_level.txt
SpacemanX-0.99.dist-info/RECORD
