Metadata-Version: 2.1
Name: SpacemanX
Version: 0.99
Summary: SpacemanX is a module used to create space (make room) between semi-width and full-width characters.
Home-page: https://github.com/Droidtown/SpacemanX
Author: Droidtown Linguistic Tech. Co. Ltd.
Author-email: info@droidtown.co
License: MIT License
Project-URL: Source, https://github.com/Droidtown/SpacemanX
Keywords: NLP,Chinese word segmentation,computational linguistics,language,linguistics,natural language,natural language processing,natural language understanding,parsing,syntax,text analytics
Classifier: Programming Language :: Python :: 3
Classifier: Programming Language :: Python :: 3 :: Only
Classifier: Programming Language :: Python :: 3.6
Classifier: Programming Language :: Python :: 3.7
Classifier: Programming Language :: Python :: 3.8
Classifier: Programming Language :: Python :: 3.9
Classifier: Programming Language :: Python :: 3.10
Classifier: License :: OSI Approved :: MIT License
Classifier: Operating System :: OS Independent
Classifier: Development Status :: 5 - Production/Stable
Classifier: Intended Audience :: Developers
Classifier: Natural Language :: Chinese (Traditional)
Classifier: Topic :: Software Development :: Libraries :: Python Modules
Classifier: Topic :: Text Processing
Classifier: Topic :: Text Processing :: Linguistic
Classifier: Topic :: Utilities
Requires-Python: >=3.6.1
License-File: LICENSE
